scmopy/LICENSE
scmopy/__init__.py
scmopy/base.py
scmopy/gaussian_scm.py
scmopy/model_selection.py
scmopy/nongaussian_scm.py
scmopy/components/__init__.py
scmopy/components/syniv.py
scmopy-0.1.5.dist-info/LICENSE
scmopy-0.1.5.dist-info/METADATA
scmopy-0.1.5.dist-info/WHEEL
scmopy-0.1.5.dist-info/top_level.txt
scmopy-0.1.5.dist-info/RECORD
