Metadata-Version: 2.1
Name: scmopy
Version: 0.1.5
Summary: scmopy: Distribution-Agnostic Structural Causal Models Optimization in Python
Home-page: https://github.com/DSsoli/scmopy.git
Author: Sanghoon Lee (DSsoli)
Author-email: solisoli3197@gmail.com
License-File: LICENSE
Requires-Dist: numpy
Requires-Dist: pandas
Requires-Dist: scipy
